{
  "id": "1498495",
  "name": "no name",
  "font_family": "iconfont",
  "css_prefix_text": "icon-",
  "description": "",
  "glyphs": [
    {
      "icon_id": "1069748",
      "name": "返回顶部",
      "font_class": "fanhuidingbu",
      "unicode": "e65b",
      "unicode_decimal": 58971
    },
    {
      "icon_id": "1284626",
      "name": "支付宝支付",
      "font_class": "zhifubaozhifu",
      "unicode": "e64f",
      "unicode_decimal": 58959
    },
    {
      "icon_id": "1287310",
      "name": "图标_返回顶部",
      "font_class": "tubiao_fanhuidingbu",
      "unicode": "e612",
      "unicode_decimal": 58898
    },
    {
      "icon_id": "3506928",
      "name": "qq",
      "font_class": "qq",
      "unicode": "e600",
      "unicode_decimal": 58880
    },
    {
      "icon_id": "3900981",
      "name": "手机",
      "font_class": "tubiaozhizuomoban",
      "unicode": "e630",
      "unicode_decimal": 58928
    },
    {
      "icon_id": "4333456",
      "name": "写字",
      "font_class": "xiezi",
      "unicode": "e60e",
      "unicode_decimal": 58894
    },
    {
      "icon_id": "5098251",
      "name": "icon_百度logo",
      "font_class": "icon_baidulogo",
      "unicode": "e65e",
      "unicode_decimal": 58974
    },
    {
      "icon_id": "5427697",
      "name": "微信",
      "font_class": "weixin",
      "unicode": "e620",
      "unicode_decimal": 58912
    },
    {
      "icon_id": "7974083",
      "name": "手机",
      "font_class": "shouji",
      "unicode": "e604",
      "unicode_decimal": 58884
    },
    {
      "icon_id": "9186712",
      "name": "微博",
      "font_class": "weibo",
      "unicode": "e666",
      "unicode_decimal": 58982
    }
  ]
}
